io_collection/__init__.py
io_collection/__main__.py
io_collection/keys/__init__.py
io_collection/keys/change_key.py
io_collection/keys/check_key.py
io_collection/keys/copy_key.py
io_collection/keys/get_keys.py
io_collection/keys/group_keys.py
io_collection/keys/make_key.py
io_collection/keys/remove_key.py
io_collection/load/__init__.py
io_collection/load/load_buffer.py
io_collection/load/load_dataframe.py
io_collection/load/load_image.py
io_collection/load/load_json.py
io_collection/load/load_pickle.py
io_collection/load/load_tar.py
io_collection/load/load_text.py
io_collection/py.typed
io_collection/quilt/__init__.py
io_collection/quilt/load_quilt_package.py
io_collection/quilt/save_quilt_item.py
io_collection/save/__init__.py
io_collection/save/save_buffer.py
io_collection/save/save_dataframe.py
io_collection/save/save_figure.py
io_collection/save/save_gif.py
io_collection/save/save_image.py
io_collection/save/save_json.py
io_collection/save/save_pickle.py
io_collection/save/save_tar.py
io_collection/save/save_text.py
io_collection-1.1.0.dist-info/LICENSE
io_collection-1.1.0.dist-info/METADATA
io_collection-1.1.0.dist-info/WHEEL
io_collection-1.1.0.dist-info/RECORD
