Metadata-Version: 2.1
Name: io-collection
Version: 1.1.0
Summary: Collection of tasks for I/O.
License: BSD-3-Clause
Author: Jessica S. Yu
Author-email: jesyu@uw.edu
Requires-Python: >=3.9,<4.0
Classifier: License :: OSI Approved :: BSD License
Classifier: Programming Language :: Python :: 3
Classifier: Programming Language :: Python :: 3.9
Classifier: Programming Language :: Python :: 3.10
Classifier: Programming Language :: Python :: 3.11
Classifier: Programming Language :: Python :: 3.12
Provides-Extra: images
Requires-Dist: bioio (>=1.0.0,<2.0.0) ; extra == "images"
Requires-Dist: bioio-ome-tiff (>=1.0.0,<2.0.0) ; extra == "images"
Requires-Dist: bioio-tifffile (>=1.0.0,<2.0.0) ; extra == "images"
Requires-Dist: boto3 (>=1.24.59,<2.0.0)
Requires-Dist: matplotlib (>=3.7.0,<4.0.0)
Requires-Dist: numpy (>=1.24.2,<2.0.0)
Requires-Dist: pandas (>=1.5.3,<2.0.0)
Requires-Dist: pillow (>=10.3.0,<11.0.0)
Requires-Dist: prefect (>=2.8.2,<3.0.0)
Requires-Dist: quilt3 (>=5.0.0,<6.0.0)
Requires-Dist: s3fs (>=2023.1.0,<2024.0.0)
